pybounce/__init__.py
pybounce/client_protocol.py
pybounce/file_manager.py
pybounce/pybounce.py
pybounce/sqlite_manager.py
pybounce-0.2.0.dist-info/METADATA
pybounce-0.2.0.dist-info/WHEEL
pybounce-0.2.0.dist-info/entry_points.txt
pybounce-0.2.0.dist-info/RECORD
