Metadata-Version: 2.3
Name: pybounce
Version: 0.2.0
Summary: Automatically upload music bounces to a Telegram channel
Author: Danny Stewart
Author-email: danny@stewart.cc
Requires-Python: >=3.12
Classifier: Programming Language :: Python :: 3
Classifier: Programming Language :: Python :: 3.12
Classifier: Programming Language :: Python :: 3.13
Requires-Dist: dsbase (>=0.3.4,<0.4.0)
Requires-Dist: inquirer (>=3.4.0,<4.0.0)
Requires-Dist: mutagen (>=1.47.0,<2.0.0)
Requires-Dist: telethon (>=1.39.0,<2.0.0)
Requires-Dist: tqdm (>=4.67.1,<5.0.0)
